README.md
setup.py
hamonsoft/__init__.py
hamonsoft/database/__init__.py
hamonsoft/database/datasource.py
hamonsoft/database/db_pool.py
hamonsoft/database/db_wrapper.py
hamonsoft/database/session_manager.py
hamonsoft/database/_impala/__init__.py
hamonsoft/database/_impala/impala.py
hamonsoft/database/_impala/impala_pool.py
hamonsoft/database/_mysql/__init__.py
hamonsoft/database/_mysql/mysql.py
hamonsoft/database/_mysql/mysql_pool.py
hamonsoft/database/_utils/__init__.py
hamonsoft/database/_utils/loder.py
hamonsoft_ai_database.egg-info/PKG-INFO
hamonsoft_ai_database.egg-info/SOURCES.txt
hamonsoft_ai_database.egg-info/dependency_links.txt
hamonsoft_ai_database.egg-info/requires.txt
hamonsoft_ai_database.egg-info/top_level.txt