Metadata-Version: 2.1
Name: hamonsoft-ai-database
Version: 0.0.17
Summary: Hamonsoft Company Database Python Version Package
Author: Hamonsoft AI
License: MIT
Requires-Python: >=3.8, <4
Requires-Dist: mysql-connector-python==9.0.0
Requires-Dist: impyla==0.19.0
